Metadata-Version: 1.2
Name: socks5server
Version: 0.1.0
Summary: A simple asyncio-based socks5 server
Home-page: https://github.com/matt-snider/socks5
Author: matt-snider
Author-email: matt.snider@protonmail.com
License: UNKNOWN
Project-URL: Source, https://github.com/matt-snider/socks5
Keywords: socks socks5 proxy asyncio
Platform: UNKNOWN
Classifier: Development Status :: 3 - Alpha
Classifier: Intended Audience :: Developers
Classifier: License :: OSI Approved :: MIT License
Classifier: Programming Language :: Python :: 3.6
Classifier: Programming Language :: Python :: 3.7
Requires-Python: >=3.6
